{
	"questions_list": [{
		"q": "参加工作有一年，目前还是单身。\n妈妈：“你看看隔壁老王家都抱上孙子啦！你成天在家里躺着能认识姑娘？”\n",
		"a": [{
			"desc": "是啊，老王都抱孙子，\b你还不帮我找个儿子。"
		}, {
			"desc": "我这不就是躺着等姑娘找上门来吗？"
		}, {
			"desc": "孙子满大街都是，你想抱哪个？"
		}, {
			"desc": "我才刚毕业不久，现在正是需要好好工作的时候，处对象过两年再说吧！"
		}]
	}, {
		"q": "因为带东西回家太麻烦，你回家没带什么。\n邻居：“我女儿今年给我买了洗碗机，唉，现在的孩子就爱花这些钱。xx啊，你给爸妈带了什么礼物呀？”\n",
		"a": [{
			"desc": "礼物有啥用，还是人民币比较实在。"
		}, {
			"desc": "现在市道不好，年轻人大手大脚的要不得。"
		}, {
			"desc": "我给爸妈带了笑容。"
		}, {
			"desc": "太麻烦了，我工作的地方也没什么好买的，就没有带。"
		}]
	}, {
		"q": "初一，大姨带着表弟来你家做客。\b\n小姨：“你表弟的学习成绩很差，不喜欢学习。这次过年就让他住在你家了，你难得回家，好好辅导他写作业啊。”\n",
		"a": [{
			"desc": "我学习成绩这么差，哪能辅导了表弟呢？还是另请高明吧。"
		}, {
			"desc": "应该给小孩多一些空间和自由，以后他会感谢你的。"
		}, {
			"desc": "不要用战术上的勤奋对抗战略上的懒惰。"
		}, {
			"desc": "我这个假期还要学Python，应该没有什么时间辅导他。"
		}]
	}, {
		"q": "过年同学聚会，酒桌上。\n老同学：“你今年年终奖发了多少啊？”\n",
		"a": [{
			"desc": "肯定没有你多呀，哪里有你混的好。"
		}, {
			"desc": "先把欠我三个月的工资发给我，我就满足了。"
		}, {
			"desc": "还好，现在个人税少扣了很多，也是一笔收入。"
		}, {
			"desc": "不想说了，那个公司不行，来年打算要换工作了 。"
		}]
	}, {
		"q": "一个不太熟悉的朋友和你打招呼。\n朋友：“诶！怎么一年不见，长胖了那么多。”\n",
		"a": [{
			"desc": "是啊，一年不见，你头发也少了好多。"
		}, {
			"desc": "没办法，都怪对象做饭太好吃了。"
		}, {
			"desc": "一年不见，想不到你都瞎了。"
		}, {
			"desc": "是啊，工作太忙都没时间去锻炼。"
		}]
	}, {
		"q": "刚参加工作两年，目前处于事业起步阶段。\n小姑：“每天起早贪黑的，一年能挣多少钱啊？什么时候买房？”\n",
		"a": [{
			"desc": "你每天起早贪黑地照顾小孩，他高考能得几分啊，能上清华不？"
		}, {
			"desc": "挣得不多，正好看中了一套，回头跟你借点。"
		}, {
			"desc": "钱会有的，房子也会有的。"
		}, {
			"desc": "现在房价太贵了，我才毕业两年哪买得起。"
		}]
	}, {
		"q": "你刚结婚不久，暂时还没打算要孩子。\n大姨：“该生小孩了，年纪大了再生，身体难恢复。现在你爸妈还年轻能给你带小孩，多好呀！”\n",
		"a": [{
			"desc": "您那么早生的怎么还没有恢复过来？"
		}, {
			"desc": "先让爸妈休息几年吧，刚不用管我了，又要带小孩子，太辛苦了。"
		}, {
			"desc": "一百年太久，只争朝夕。"
		}, {
			"desc": "穷的叮当响，奶粉钱都攒不够，等有钱再考虑吧。"
		}]
	}, {
		"q": "你今年即将毕业，但还没找到工作。\n大舅：“今年毕业了啊，找了什么工作啊。\b能养得起自己不？”\n",
		"a": [{
			"desc": "不能。"
		}, {
			"desc": "最近学习事情比较多，还没来得及找。不过已经对比了几家不错的公司。准备投简历。"
		}, {
			"desc": "养得起自己算什么，刘强东养起了一条村子。"
		}, {
			"desc": "我还没开始找工作，过完年再说吧。"
		}]
	}],
	"result": {
		"1": [{
			"topic": "霸气十猪",
			"performance": "应对灵魂拷问表现得高冷、霸气，\b用强大的气势压倒对方。威猛虽好，对待亲友记得注意分寸哦~"
		}],
		"2": [{
			"topic": "妙语连猪",
			"performance": "应对灵魂拷问表现得机灵、智慧，让再难缠的人都挑不出不是。新春拜年适合用甜言蜜语主动出击，赢取亲友的喜爱。"
		}, {
			"topic": "美中不猪",
			"performance": "应对灵魂拷问表象得优雅、大方，丝毫没有显露出生涩、不合适。新春拜年适合一马当先，为人挡“怼”。"
		}],
		"3": [{
			"topic": "字字猪玑",
			"performance": "应对灵魂拷问表象得神秘、空灵，让人感觉猜不透摸不着。新春拜年适合\b翘手旁观，笑看风云。"
		}],
		"4": [{
			"topic": "猪不出户",
			"performance": "应对灵魂拷问表现得生涩、害羞，目前应对拷问的\b经验还不够。今年新春不适合面对“唇枪舌战”，还是在家好好休息吧。　"
		}]
	}
}